[
	{
		"anonymous": false,
		"inputs": [
			{
				"indexed": false,
				"internalType": "string",
				"name": "domainName",
				"type": "string"
			},
			{
				"indexed": false,
				"internalType": "address",
				"name": "owner",
				"type": "address"
			}
		],
		"name": "DomainRegistered",
		"type": "event"
	},
	{
		"anonymous": false,
		"inputs": [
			{
				"indexed": false,
				"internalType": "string",
				"name": "domainName",
				"type": "string"
			},
			{
				"indexed": false,
				"internalType": "string",
				"name": "recordType",
				"type": "string"
			}
		],
		"name": "RecordUpdated",
		"type": "event"
	},
	{
		"inputs": [
			{
				"internalType": "string",
				"name": "_domainName",
				"type": "string"
			}
		],
		"name": "registerDomain",
		"outputs": [],
		"stateMutability": "nonpayable",
		"type": "function"
	},
	{
		"inputs": [
			{
				"internalType": "string",
				"name": "_domainName",
				"type": "string"
			},
			{
				"internalType": "string",
				"name": "_aRecord",
				"type": "string"
			}
		],
		"name": "updateARecord",
		"outputs": [],
		"stateMutability": "nonpayable",
		"type": "function"
	},
	{
		"inputs": [
			{
				"internalType": "string",
				"name": "_domainName",
				"type": "string"
			},
			{
				"internalType": "string",
				"name": "_cnameRecord",
				"type": "string"
			}
		],
		"name": "updateCNAMERecord",
		"outputs": [],
		"stateMutability": "nonpayable",
		"type": "function"
	},
	{
		"inputs": [
			{
				"internalType": "string",
				"name": "_domainName",
				"type": "string"
			},
			{
				"internalType": "string",
				"name": "_txtRecord",
				"type": "string"
			}
		],
		"name": "updateTXTRecord",
		"outputs": [],
		"stateMutability": "nonpayable",
		"type": "function"
	},
	{
		"inputs": [
			{
				"internalType": "string",
				"name": "_domainName",
				"type": "string"
			}
		],
		"name": "getRecords",
		"outputs": [
			{
				"internalType": "address",
				"name": "",
				"type": "address"
			},
			{
				"internalType": "string",
				"name": "",
				"type": "string"
			},
			{
				"internalType": "string",
				"name": "",
				"type": "string"
			},
			{
				"internalType": "string",
				"name": "",
				"type": "string"
			}
		],
		"stateMutability": "view",
		"type": "function"
	},
	{
		"inputs": [
			{
				"internalType": "bytes32",
				"name": "",
				"type": "bytes32"
			}
		],
		"name": "records",
		"outputs": [
			{
				"internalType": "address",
				"name": "owner",
				"type": "address"
			},
			{
				"internalType": "string",
				"name": "a_record",
				"type": "string"
			},
			{
				"internalType": "string",
				"name": "cname_record",
				"type": "string"
			},
			{
				"internalType": "string",
				"name": "txt_record",
				"type": "string"
			}
		],
		"stateMutability": "view",
		"type": "function"
	}
]
